pynegex/__init__.py
pynegex/model/__init__.py
pynegex/model/negex.py
pynegex/model/runners.py
pynegex/model/triggersets/chapman-en.txt
pynegex/model/triggersets/cotik-de.txt
pynegex-0.0.3.dev0.dist-info/LICENSE
pynegex-0.0.3.dev0.dist-info/METADATA
pynegex-0.0.3.dev0.dist-info/WHEEL
pynegex-0.0.3.dev0.dist-info/top_level.txt
pynegex-0.0.3.dev0.dist-info/RECORD
