Metadata-Version: 2.1
Name: pynegex
Version: 0.0.3.dev0
Summary: Pypi package for negex with multilingual support
Author: Moe Bin Sumait
Author-email: mh.binsumait@gmail.com
Classifier: Programming Language :: Python
Classifier: Operating System :: OS Independent
Requires-Python: >=3.6
License-File: LICENSE
